bundlemanager
bundlemanager_tornado
setup.py
bundlemaker/__init__.py
bundlemaker/bundlemaker.py
bundlemaker/settings.py
bundlemaker/templates/bundle.json
bundlemaker/templates/debundler.js
bundlemaker/templates/debundler_template.html.j2
bundlemanager.egg-info/PKG-INFO
bundlemanager.egg-info/SOURCES.txt
bundlemanager.egg-info/dependency_links.txt
bundlemanager.egg-info/requires.txt
bundlemanager.egg-info/top_level.txt