Metadata-Version: 1.1
Name: bundlemanager
Version: 1.0.5
Summary: DDeflect bundle management system
Home-page: http://github.com/equalitie/DDeflect
Author: Hugh Nowlan
Author-email: nosmo@nosmo.me
License: Hacktivismo Enhanced-Source Software License Agreement
Keywords: deflect bundler cms reverseproxy
Platform: UNKNOWN
Classifier: Development Status :: 5 - Production/Stable
Classifier: Intended Audience :: Developers
Classifier: Intended Audience :: System Administrators
Classifier: Topic :: Utilities
